json_fix/__init__.py
json_fix-1.0.1.dist-info/METADATA
json_fix-1.0.1.dist-info/WHEEL
json_fix-1.0.1.dist-info/top_level.txt
json_fix-1.0.1.dist-info/RECORD
