Metadata-Version: 2.4
Name: json_fix
Version: 1.0.1
Summary: allow custom class json behavior on builtin json object
Home-page: https://github.com/jeff-hykin/json_fix.git
Author: Jeff Hykin
Author-email: jeff.hykin@gmail.com
License: MIT
Requires-Python: >=3.6
Dynamic: author
Dynamic: author-email
Dynamic: description
Dynamic: description-content-type
Dynamic: home-page
Dynamic: license
Dynamic: requires-python
Dynamic: summary
